secureml/__init__.py
secureml/anonymization.py
secureml/audit.py
secureml/cli.py
secureml/compliance.py
secureml/federated.py
secureml/isolated_environments/__init__.py
secureml/isolated_environments/tf_privacy.py
secureml/isolated_environments/tf_privacy_trainer.py
secureml/key_management/README.md
secureml/key_management/__init__.py
secureml/presets/__init__.py
secureml/presets/ccpa.yaml
secureml/presets/gdpr.yaml
secureml/presets/hipaa.yaml
secureml/presets/lgpd.yaml
secureml/privacy.py
secureml/reporting.py
secureml/synthetic.py
secureml/templates/__init__.py
secureml-0.3.1.dist-info/LICENSE
secureml-0.3.1.dist-info/METADATA
secureml-0.3.1.dist-info/WHEEL
secureml-0.3.1.dist-info/entry_points.txt
secureml-0.3.1.dist-info/RECORD
