Metadata-Version: 2.3
Name: secureml
Version: 0.3.1
Summary: A Python library for privacy-preserving machine learning
License: MIT
Keywords: machine learning,privacy,security,compliance,gdpr
Author: Enzo Paloschi Biondo
Author-email: enzobiondo11@outlook.com
Requires-Python: >=3.11,<3.14
Classifier: License :: OSI Approved :: MIT License
Classifier: Programming Language :: Python :: 3
Classifier: Programming Language :: Python :: 3.11
Classifier: Programming Language :: Python :: 3.12
Classifier: Programming Language :: Python :: 3.13
Provides-Extra: pdf
Provides-Extra: vault
Requires-Dist: click (>=8.1.8,<9.0.0)
Requires-Dist: faker (>=37.0.1,<38.0.0)
Requires-Dist: flwr[simulation] (>=1.19.0,<2.0.0)
Requires-Dist: hvac (>=1.1.1,<2.0.0) ; extra == "vault"
Requires-Dist: jinja2 (>=3.1.4,<4.0.0)
Requires-Dist: matplotlib (>=3.10.3,<4.0.0)
Requires-Dist: numpy (>=2.3.0,<3.0.0)
Requires-Dist: opacus (>=1.5.4,<2.0.0)
Requires-Dist: pandas (>=2.3.0,<3.0.0)
Requires-Dist: polars (>=1.30.0,<2.0.0)
Requires-Dist: pyarrow (>=19.0.1,<20.0.0)
Requires-Dist: pydantic (>=2.11.3,<3.0.0)
Requires-Dist: pyyaml (==6.0.2)
Requires-Dist: scikit-learn (>=1.7.0,<2.0.0)
Requires-Dist: sdv
Requires-Dist: spacy (>=3.8.7,<4.0.0)
Requires-Dist: sphinx-rtd-theme (>=1.3.0,<2.0.0)
Requires-Dist: torch (>=2.7.1,<3.0.0)
Requires-Dist: weasyprint (>=64.1,<65.0) ; extra == "pdf"
Project-URL: Documentation, https://secureml.readthedocs.io
Project-URL: Repository, https://github.com/scimorph/secureml
